{
  "version": "5",
  "dialect": "pg",
  "id": "fae8d0bf-313e-41b7-b65c-4c26564a63ad",
  "prevId": "7c1f9af1-44f3-4503-a664-49b089c9f217",
  "tables": {
    "movies": {
      "name": "movies",
      "schema": "",
      "columns": {
        "id": {
          "name": "id",
          "type": "serial",
          "primaryKey": true,
          "notNull": true
        },
        "user_id": {
          "name": "user_id",
          "type": "varchar(36)",
          "primaryKey": false,
          "notNull": false
        },
        "title": {
          "name": "title",
          "type": "varchar(256)",
          "primaryKey": false,
          "notNull": false
        },
        "poster_url": {
          "name": "poster_url",
          "type": "text",
          "primaryKey": false,
          "notNull": false
        },
        "imdb_url": {
          "name": "imdb_url",
          "type": "text",
          "primaryKey": false,
          "notNull": false
        },
        "rating": {
          "name": "rating",
          "type": "numeric(3, 2)",
          "primaryKey": false,
          "notNull": false
        },
        "created_at": {
          "name": "created_at",
          "type": "timestamp",
          "primaryKey": false,
          "notNull": false,
          "default": "now()"
        }
      },
      "indexes": {},
      "foreignKeys": {},
      "compositePrimaryKeys": {},
      "uniqueConstraints": {}
    }
  },
  "enums": {},
  "schemas": {},
  "_meta": {
    "schemas": {},
    "tables": {},
    "columns": {}
  }
}